scce/__init__.py
scce/analyse/__init__.py
scce/analyse/attribution.py
scce/analyse/chromatin_remodeling.py
scce/data.py
scce/integrate.py
scce/model/__init__.py
scce/model/dataset.py
scce/model/focalloss.py
scce/model/net.py
scce/model/train_model.py
scce/model/util.py
scce/model/validate.py
scce/plot/__init__.py
scce/plot/base.py
scce/plot/view.py
scce/preprocess.py
scce/utils.py
scce-0.1.2.dist-info/LICENSE
scce-0.1.2.dist-info/METADATA
scce-0.1.2.dist-info/WHEEL
scce-0.1.2.dist-info/RECORD
