Metadata-Version: 2.1
Name: scce
Version: 0.1.2
Summary: a Single-cell method for predicting Chromatin Conformation based on gene Expression
Home-page: https://github.com/LMH0066/SEE
License: Apache-2.0
Keywords: bioinformatics,deep-learning,single-cell
Author: liminghong.dev
Author-email: lmh0066@outlook.com
Requires-Python: >=3.8,<4.0
Classifier: License :: OSI Approved :: Apache Software License
Classifier: Programming Language :: Python :: 3
Classifier: Programming Language :: Python :: 3.8
Classifier: Programming Language :: Python :: 3.9
Classifier: Programming Language :: Python :: 3.10
Classifier: Programming Language :: Python :: 3.11
Requires-Dist: captum (>=0.6.0,<0.7.0)
Requires-Dist: fanc (>=0.9.25,<0.10.0)
Requires-Dist: pybigwig (==0.3.20)
Requires-Dist: scglue (>=0.3.2,<0.4.0)
Requires-Dist: setuptools (>=67.6.1,<68.0.0)
Requires-Dist: tensorboard (>=2.13.0,<3.0.0)
Requires-Dist: torch-tb-profiler (>=0.4.1,<0.5.0)
Requires-Dist: vit-pytorch (>=1.2.0,<2.0.0)
Project-URL: Repository, https://github.com/LMH0066/SEE
